COPYING.md
LICENSE.md
README.md
pyproject.toml
jsonmagic/__init__.py
jsonmagic/magic.py
jsonmagic.egg-info/PKG-INFO
jsonmagic.egg-info/SOURCES.txt
jsonmagic.egg-info/dependency_links.txt
jsonmagic.egg-info/requires.txt
jsonmagic.egg-info/top_level.txt