Metadata-Version: 2.4
Name: jsonmagic
Version: 0.0.2
Summary: A magic that displays an object using JupyterLab's rich display JSON renderer
Maintainer-email: Dominic Kempf <dominic.kempf@iwr.uni-heidelberg.de>
License: MIT
Classifier: Programming Language :: Python :: 3
Classifier: Operating System :: OS Independent
Requires-Python: >=3.10
License-File: LICENSE.md
License-File: COPYING.md
Requires-Dist: IPython
Dynamic: license-file
